django_multiselectfield-1.0.0.dist-info/licenses/COPYING.LGPLv3
multiselectfield/__init__.py
multiselectfield/apps.py
multiselectfield/utils.py
multiselectfield/validators.py
multiselectfield/db/__init__.py
multiselectfield/db/fields.py
multiselectfield/forms/__init__.py
multiselectfield/forms/fields.py
multiselectfield/forms/widgets.py
multiselectfield/locale/es/LC_MESSAGES/django.mo
multiselectfield/locale/es/LC_MESSAGES/django.po
multiselectfield/static/multiselectfield/css/admin-multiselectfield.css
multiselectfield/static/sortmultiselectfield/sortmultiselectfield.css
multiselectfield/static/sortmultiselectfield/sortmultiselectfield.js
django_multiselectfield-1.0.0.dist-info/METADATA
django_multiselectfield-1.0.0.dist-info/WHEEL
django_multiselectfield-1.0.0.dist-info/top_level.txt
django_multiselectfield-1.0.0.dist-info/RECORD
