Metadata-Version: 2.4
Name: django-multiselectfield
Version: 1.0.0
Summary: Django multiple select field
Home-page: https://github.com/goinnn/django-multiselectfield
Author: Pablo Martin
Author-email: goinnn@gmail.com
License: LGPL 3
Keywords: django,multiple,select,field,choices
Classifier: Development Status :: 4 - Beta
Classifier: Framework :: Django
Classifier: License :: OSI Approved :: GNU Library or Lesser General Public License (LGPL)
Classifier: Programming Language :: Python :: 3.8
Classifier: Programming Language :: Python :: 3.9
Classifier: Programming Language :: Python :: 3.10
Classifier: Programming Language :: Python :: 3.11
Classifier: Programming Language :: Python :: 3.12
Classifier: Framework :: Django :: 3.2
Classifier: Framework :: Django :: 4.2
Classifier: Framework :: Django :: 5.0
Classifier: Framework :: Django :: 5.1
License-File: COPYING.LGPLv3
Requires-Dist: django>=3.2
Dynamic: author
Dynamic: author-email
Dynamic: classifier
Dynamic: description
Dynamic: home-page
Dynamic: keywords
Dynamic: license
Dynamic: license-file
Dynamic: requires-dist
Dynamic: summary
